LICENSE
MANIFEST.in
README.rst
pyproject.toml
setup.cfg
setup.py
django_site/__init__.py
django_site/admin.py
django_site/apps.py
django_site/models.py
django_site/signals.py
django_site/tests.py
django_site/views.py
django_site/locale/__init__.py
django_site/migrations/0001_initial.py
django_site/migrations/__init__.py
django_site_extend.egg-info/PKG-INFO
django_site_extend.egg-info/SOURCES.txt
django_site_extend.egg-info/dependency_links.txt
django_site_extend.egg-info/requires.txt
django_site_extend.egg-info/top_level.txt
riso/__init__.py
riso/asgi.py
riso/settings.py
riso/urls.py
riso/wsgi.py